jsonable_objects/__init__.py
jsonable_objects/interfaces.py
jsonable_objects/proxy.py
jsonable_objects-0.1.5.dist-info/METADATA
jsonable_objects-0.1.5.dist-info/RECORD
jsonable_objects-0.1.5.dist-info/WHEEL
jsonable_objects-0.1.5.dist-info/top_level.txt
